bandersnatch_updated_plugin/__init__.py
bandersnatch_updated_plugin/updated.py
bandersnatch_updated_plugin-0.1.0.dist-info/LICENSE.txt
bandersnatch_updated_plugin-0.1.0.dist-info/METADATA
bandersnatch_updated_plugin-0.1.0.dist-info/WHEEL
bandersnatch_updated_plugin-0.1.0.dist-info/entry_points.txt
bandersnatch_updated_plugin-0.1.0.dist-info/top_level.txt
bandersnatch_updated_plugin-0.1.0.dist-info/RECORD
